shipyard_airtable/__init__.py
shipyard_airtable/airtable.py
shipyard_airtable/cli/__init__.py
shipyard_airtable/cli/authtest.py
shipyard_airtable/cli/download_file.py
shipyard_airtable/cli/upload.py
shipyard_airtable-0.1.2.dist-info/METADATA
shipyard_airtable-0.1.2.dist-info/WHEEL
shipyard_airtable-0.1.2.dist-info/RECORD
