Metadata-Version: 2.1
Name: shipyard-airtable
Version: 0.1.2
Summary: A local client to work with Airtable
License: Apache 2.0
Author: wrp801
Author-email: wespoulsen@gmail.com
Requires-Python: >=3.9,<4.0
Classifier: License :: Other/Proprietary License
Classifier: Programming Language :: Python :: 3
Classifier: Programming Language :: Python :: 3.9
Classifier: Programming Language :: Python :: 3.10
Classifier: Programming Language :: Python :: 3.11
Requires-Dist: pandas (>=2.2.0,<3.0.0)
Requires-Dist: pyairtable (==2.2.2)
Requires-Dist: shipyard-bp-utils (==1.0.1)
Requires-Dist: shipyard-templates (==0.6.1)
